revdownloader/__init__.py
revdownloader/core.py
revdownloader/downloader.py
tests/__init__.py
tests/test_downloader.py
revdownloader-0.1.8.dist-info/METADATA
revdownloader-0.1.8.dist-info/WHEEL
revdownloader-0.1.8.dist-info/top_level.txt
revdownloader-0.1.8.dist-info/RECORD
