Metadata-Version: 2.4
Name: revdownloader
Version: 0.1.8
Summary: Librería para descarga de archivos
Home-page: https://github.com/tuusuario/revdownloader
Author: Tu Nombre
Author-email: Tu Nombre <tu@email.com>
Project-URL: Homepage, https://github.com/tuusuario/revdownloader
Project-URL: Bug Tracker, https://github.com/tuusuario/revdownloader/issues
Classifier: Programming Language :: Python :: 3
Classifier: License :: OSI Approved :: MIT License
Classifier: Operating System :: OS Independent
Requires-Python: >=3.7
Dynamic: author
Dynamic: home-page
Dynamic: requires-python
